CHANGELOG.md
dunamai_formatters/__init__.py
dunamai_formatters/helpers.py
dunamai_formatters/pep440.py
dunamai_formatters/py.typed
dunamai_formatters-0.1.0.dist-info/LICENSE
dunamai_formatters-0.1.0.dist-info/WHEEL
dunamai_formatters-0.1.0.dist-info/METADATA
dunamai_formatters-0.1.0.dist-info/RECORD
